[
  {
    "url": "https://videos.pshar.ma/prism-fl/",
    "text": "\"Don't Say Gay\" Video Links"
  },
  {
    "url": "https://instagram.com/pepsi.media",
    "text": "My Instagram page"
  },
  {
    "url": "https://mylifeinuni.com",
    "text": "My Life In University Project Page"
  },
  {
    "url": "https://ukrainecrisisappeal.org",
    "text": "Ukraine Crisis Appeal (Charity)"
  },
  {
    "url": "https://hsc.one",
    "text": "HSCOne"
  },
  {
    "url": "https://blacklivesmatter.com/",
    "text": "Black Lives Matter"
  },
  {
    "url": "https://eji.org/",
    "text": "The Equal Justice Initiative"
  }
]
